{
    "configurations": [
        {
            "name": "Win32",
            "includePath": [
                "${workspaceFolder}/**",
                "${workspaceFolder}/Core/Inc",
                "${workspaceFolder}/Drivers/STM32F4xx_HAL_Driver/Inc",
                "${workspaceFolder}/Drivers/STM32F4xx_HAL_Driver/Inc/Legacy",
                "${workspaceFolder}/Drivers/CMSIS/Device/ST/STM32F4xx/Include",
                "${workspaceFolder}/Drivers/CMSIS/Include"
            ],
            "defines": [
                "DEBUG",
                "USE_HAL_DRIVER",
                "STM32F411xE"
            ],
            "windowsSdkVersion": "10.0.18362.0",
            "compilerPath": "C:/gnuarmemb/bin/arm-none-eabi-g++",
            "cppStandard": "c++17",
            "intelliSenseMode": "windows-gcc-arm"
        }
    ],
    "version": 4
}